lof.py
lof_fund-1.1.4.dist-info/METADATA
lof_fund-1.1.4.dist-info/WHEEL
lof_fund-1.1.4.dist-info/entry_points.txt
lof_fund-1.1.4.dist-info/top_level.txt
lof_fund-1.1.4.dist-info/RECORD
