Metadata-Version: 2.2
Name: lof-fund
Version: 1.1.4
Summary: 获取基金溢价率的脚本
Author: Egg*4
Author-email: 1127885315@qq.com
Classifier: Programming Language :: Python :: 3
Classifier: License :: OSI Approved :: MIT License
Classifier: Operating System :: OS Independent
Requires-Python: >=3.9
Requires-Dist: chinesecalendar
Requires-Dist: schedule
Requires-Dist: requests
Requires-Dist: pandas
Requires-Dist: akshare
Requires-Dist: beautifulsoup4
Dynamic: author
Dynamic: author-email
Dynamic: classifier
Dynamic: description
Dynamic: description-content-type
Dynamic: requires-dist
Dynamic: requires-python
Dynamic: summary
